liteopt-0.1.2.dist-info/METADATA
liteopt-0.1.2.dist-info/WHEEL
liteopt/__init__.py
liteopt/liteopt.abi3.so
liteopt-0.1.2.dist-info/RECORD
