Metadata-Version: 2.4
Name: liteopt
Version: 0.1.2
Classifier: Programming Language :: Python
Classifier: Programming Language :: Python :: 3
Classifier: Programming Language :: Rust
Classifier: License :: OSI Approved :: MIT License
Classifier: Operating System :: OS Independent
Summary: Lightweight gradient descent optimizer implemented in Rust
Author-email: Taiki Ishigaki <taiki000ishigaki@gmail.com>
License: MIT
Requires-Python: >=3.8
Project-URL: Homepage, https://github.com/MathRobotics/liteopt
Project-URL: Repository, https://github.com/MathRobotics/liteopt
